nadag_innmelding_python_client/__init__.py
nadag_innmelding_python_client/api/__init__.py
nadag_innmelding_python_client/api/default/__init__.py
nadag_innmelding_python_client/api/default/delete_nadag_innmelding_v_1_geoteknisk_unders_geoteknisk_unders_id.py
nadag_innmelding_python_client/api/default/delete_nadag_innmelding_v_1_geoteknisk_unders_geoteknisk_unders_id_unders_pkt_geoteknisk_borehull_id.py
nadag_innmelding_python_client/api/default/get_kodeliste_code_list_name.py
nadag_innmelding_python_client/api/default/get_kodeliste_code_list_name_code_name.py
nadag_innmelding_python_client/api/default/get_nadag_innmelding_v_1_geoteknisk_borehull.py
nadag_innmelding_python_client/api/default/get_nadag_innmelding_v_1_geoteknisk_borehull_geoteknisk_borehull_id.py
nadag_innmelding_python_client/api/default/get_nadag_innmelding_v_1_geoteknisk_unders.py
nadag_innmelding_python_client/api/default/get_nadag_innmelding_v_1_geoteknisk_unders_geoteknisk_unders_id.py
nadag_innmelding_python_client/api/default/get_nadag_innmelding_v_1_geoteknisk_unders_geoteknisk_unders_id_unders_pkt_geoteknisk_borehull_id.py
nadag_innmelding_python_client/api/default/get_validation_diagnostics_from_root_root_lokal_id_root_versjon_id.py
nadag_innmelding_python_client/api/default/get_validation_diagnostics_from_target_target_lokal_id_target_versjon_id.py
nadag_innmelding_python_client/api/default/post_nadag_innmelding_v_1_geoteknisk_unders.py
nadag_innmelding_python_client/api/default/post_nadag_innmelding_v_1_geoteknisk_unders_geoteknisk_unders_id_unders_pkt.py
nadag_innmelding_python_client/api/default/put_nadag_innmelding_v_1_geoteknisk_unders_geoteknisk_unders_id.py
nadag_innmelding_python_client/api/default/put_nadag_innmelding_v_1_geoteknisk_unders_geoteknisk_unders_id_unders_pkt_geoteknisk_borehull_id.py
nadag_innmelding_python_client/client.py
nadag_innmelding_python_client/errors.py
nadag_innmelding_python_client/models/__init__.py
nadag_innmelding_python_client/models/akvifer_type.py
nadag_innmelding_python_client-2025.12.19.dist-info/METADATA
nadag_innmelding_python_client-2025.12.19.dist-info/WHEEL
nadag_innmelding_python_client-2025.12.19.dist-info/RECORD
