Metadata-Version: 2.4
Name: nadag-innmelding-python-client
Version: 2025.12.19
Summary: A client library for accessing Nadag innmelding API
License: MIT
Author: Jiyang Ye
Author-email: jiyang.ye@ngi.no
Maintainer: Jiyang Ye
Maintainer-email: jiyang.ye@ngi.no
Requires-Python: >=3.13,<4.0
Classifier: License :: OSI Approved :: MIT License
Classifier: Programming Language :: Python :: 3
Classifier: Programming Language :: Python :: 3.13
Classifier: Programming Language :: Python :: 3.14
Requires-Dist: attrs (>=22.2.0)
Requires-Dist: httpx (>=0.20.0,<0.29.0)
Requires-Dist: python-dateutil (>=2.8.0,<3.0.0)
